Metadata-Version: 2.1
Name: wplotlib
Version: 0.51
Summary: A library that simplifies some basic plotting.
Home-page: https://github.com/endsley/wPlotLib.git
Download-URL: https://github.com/endsley/wPlotLib/archive/refs/tags/0.51.tar.gz
Author: Chieh Wu
Author-email: chieh.t.wu@gmail.com
License: MIT
Keywords: plot,data
Classifier: Development Status :: 3 - Alpha
Classifier: Intended Audience :: Developers
Classifier: Topic :: Software Development :: Build Tools
Classifier: License :: OSI Approved :: MIT License
Classifier: Programming Language :: Python :: 3.4
Classifier: Programming Language :: Python :: 3.5
Classifier: Programming Language :: Python :: 3.6
Classifier: Programming Language :: Python :: 3.7
License-File: LICENSE
